CHANGES.txt
CONTRIBUTORS.txt
MANIFEST.in
README.txt
TODO.txt
cleanup.sh
setup.cfg
setup.py
collective/__init__.py
collective.splashdancing.egg-info/PKG-INFO
collective.splashdancing.egg-info/SOURCES.txt
collective.splashdancing.egg-info/dependency_links.txt
collective.splashdancing.egg-info/entry_points.txt
collective.splashdancing.egg-info/namespace_packages.txt
collective.splashdancing.egg-info/not-zip-safe
collective.splashdancing.egg-info/requires.txt
collective.splashdancing.egg-info/top_level.txt
collective/splashdancing/README.txt
collective/splashdancing/TODO.txt
collective/splashdancing/__init__.py
collective/splashdancing/config.py
collective/splashdancing/configure.zcml
collective/splashdancing/controlpanel-links.pt
collective/splashdancing/controlpanel.py
collective/splashdancing/event.py
collective/splashdancing/interfaces.py
collective/splashdancing/mycomposer.py
collective/splashdancing/newscomposer.py
collective/splashdancing/newsitem.py
collective/splashdancing/settings.py
collective/splashdancing/tests.py
collective/splashdancing/browser/__init__.py
collective/splashdancing/browser/composer-html-confirm.pt
collective/splashdancing/browser/composer-html-forgot.pt
collective/splashdancing/browser/composer-html.pt
collective/splashdancing/browser/composer.py
collective/splashdancing/browser/composer.pyo
collective/splashdancing/browser/configure.zcml
collective/splashdancing/browser/preview.pt
collective/splashdancing/browser/preview.py
collective/splashdancing/content/__init__.py
collective/splashdancing/content/configure.zcml
collective/splashdancing/portlets/__init__.py
collective/splashdancing/portlets/configure.zcml
collective/splashdancing/profiles/default/actions.xml
collective/splashdancing/profiles/default/factorytool.xml
collective/splashdancing/profiles/default/metadata.xml
collective/splashdancing/profiles/default/portlets.xml
collective/splashdancing/profiles/default/rolemap.xml
collective/splashdancing/profiles/default/types.xml
collective/splashdancing/tests/__init__.py
collective/splashdancing/tests/doc_tests.py
docs/HISTORY.txt
docs/INSTALL.txt
docs/LICENSE.GPL
docs/LICENSE.txt