Metadata-Version: 1.0
Name: collective.splashdancing
Version: 1.1a
Summary: Adds pictures to newsitems in singing and dancing newsletters
Home-page: http://themes.alteroo.com
Author: David Bain
Author-email: david.bain@alteroo.com
License: GPL
Keywords: news dancing pictures singing plone python newsletter
Platform: UNKNOWN
Classifier: Framework :: Plone
Classifier: Intended Audience :: Developers
Classifier: Topic :: Software Development :: Libraries :: Python Modules
Classifier: License :: OSI Approved :: GNU General Public License (GPL)
